worldnames/__init__.py
worldnames/content.py
worldnames/flow.py
worldnames/populate.py
worldnames/populatinghelpers.py
worldnames/requirments.txt
worldnames/worldnames.json
worldnames/databases/__init__.py
worldnames/databases/customdatatypes.py
worldnames/databases/my_sql.py
worldnames/databases/sqlite.py
worldnames/databases/sqlsharing.py
worldnames/exceptions/__init__.py
worldnames-0.0.8.dist-info/METADATA
worldnames-0.0.8.dist-info/WHEEL
worldnames-0.0.8.dist-info/licenses/LICENSE
worldnames-0.0.8.dist-info/RECORD
