Metadata-Version: 2.4
Name: worldnames
Version: 0.0.8
Summary: A populater for databases and generator for user information
Project-URL: Homepage, https://github.com/ayoub-abdessadak/world-names
Project-URL: Issues, https://github.com/ayoub-abdessadak/world-names/issues
Author-email: Ayoub ben Abdessadak <ayoubabdessadak1@gmail.com>
License-File: LICENSE
Classifier: License :: OSI Approved :: MIT License
Classifier: Operating System :: OS Independent
Classifier: Programming Language :: Python :: 3
Requires-Python: >=3.8
